linearcal/__init__.py
linearcal-0.1.0.dist-info/METADATA
linearcal-0.1.0.dist-info/WHEEL
linearcal-0.1.0.dist-info/RECORD
